setup.py
MeetShah/Binomialdistribution.py
MeetShah/Gaussiandistribution.py
MeetShah/Generaldistribution.py
MeetShah/__init__.py
MeetShah.egg-info/PKG-INFO
MeetShah.egg-info/SOURCES.txt
MeetShah.egg-info/dependency_links.txt
MeetShah.egg-info/not-zip-safe
MeetShah.egg-info/top_level.txt